inmanta_plugins/sops/__init__.py
inmanta_plugins/sops/editor.py
inmanta_plugins/sops/py.typed
inmanta_plugins/sops/setup.cfg
inmanta_plugins/sops/files/.gitkeep
inmanta_plugins/sops/model/_init.cf
inmanta_plugins/sops/templates/.gitkeep
pytest_inmanta_sops/__init__.py
pytest_inmanta_sops/py.typed
inmanta_module_sops-0.3.2.dist-info/METADATA
inmanta_module_sops-0.3.2.dist-info/WHEEL
inmanta_module_sops-0.3.2.dist-info/entry_points.txt
inmanta_module_sops-0.3.2.dist-info/top_level.txt
inmanta_module_sops-0.3.2.dist-info/RECORD
