Metadata-Version: 2.4
Name: inmanta-module-sops
Version: 0.3.2
Summary: Reference and use secrets defined in sops file in project repo
Author: Guillaume Everarts de Velp
Author-email: edvgui@gmail.com
License: ASL 2.0
Project-URL: Source, https://github.com/edvgui/inmanta-module-sops
Project-URL: Changelog, https://github.com/edvgui/inmanta-module-sops/blob/master/CHANGELOG.md
Requires-Dist: inmanta-module-std
Requires-Dist: inmanta-module-config
Requires-Dist: inmanta-module-files>=2.7.0
Provides-Extra: dev
Requires-Dist: inmanta-module-sops[tests]; extra == "dev"
Requires-Dist: inmanta-dev-dependencies[extension,module]; extra == "dev"
Requires-Dist: types-requests; extra == "dev"
Provides-Extra: tests
Requires-Dist: inmanta-module-sops; extra == "tests"
Requires-Dist: pytest; extra == "tests"
